pypolyclip/__init__.py
pypolyclip/polyclip.cp313-win_amd64.pyd
pypolyclip/pypolyclip.py
pypolyclip/version.py
pypolyclip/tests/__init__.py
pypolyclip/tests/test_pypolyclip.py
pypolyclip-1.2.0.dist-info/licenses/LICENSE.rst
pypolyclip-1.2.0.dist-info/METADATA
pypolyclip-1.2.0.dist-info/WHEEL
pypolyclip-1.2.0.dist-info/top_level.txt
pypolyclip-1.2.0.dist-info/RECORD
