Metadata-Version: 2.4
Name: pypolyclip
Version: 1.2.0
Summary: A python driver to the polyclip functions
Author: Pypolyclip Developers
License-Expression: BSD-3-Clause
Project-URL: Homepage, https://github.com/spacetelescope/pypolyclip
Keywords: computational geometry,polygon clipping,polygon intersection,pixelated images,CUBISM,polyclip
Classifier: Intended Audience :: Science/Research
Classifier: Natural Language :: English
Classifier: Operating System :: OS Independent
Classifier: Programming Language :: Python
Classifier: Programming Language :: Python :: 3
Classifier: Topic :: Scientific/Engineering :: Astronomy
Requires-Python: >=3.11
License-File: LICENSE.rst
Requires-Dist: numpy>=2.0
Provides-Extra: test
Requires-Dist: matplotlib>=3.9; extra == "test"
Requires-Dist: pytest-astropy>=0.11; extra == "test"
Dynamic: license-file
